beepy/__init__.py
beepy/attrs.py
beepy/children.py
beepy/components.py
beepy/context.py
beepy/framework.py
beepy/listeners.py
beepy/router.py
beepy/style.py
beepy/tags.py
beepy/trackable.py
beepy/types.py
beepy/dev/__init__.py
beepy/dev/__main__.py
beepy/dev/example.html
beepy/dev/example.py
beepy/modules/__init__.py
beepy/modules/actions.py
beepy/modules/context_menu.py
beepy/modules/local_storage.py
beepy/modules/modal.py
beepy/modules/plot.py
beepy/modules/table.py
beepy/modules/tabs.py
beepy/ssr/__init__.py
beepy/ssr/extra.js
beepy/utils/__init__.py
beepy/utils/api.py
beepy/utils/asyncio.py
beepy/utils/common.py
beepy/utils/dev.py
beepy/utils/import_hooks.py
beepy/utils/internal.py
beepy/utils/js.py
beepy/utils/js_py.py
beepy_web-10.0.0.dist-info/METADATA
beepy_web-10.0.0.dist-info/WHEEL
beepy_web-10.0.0.dist-info/licenses/LICENSE
beepy_web-10.0.0.dist-info/RECORD
