Metadata-Version: 2.1
Name: beepy-web
Version: 10.0.0
Summary: The modern frontend web framework for Python
Project-URL: Homepage, https://beepy-web-ba63e5a12994.herokuapp.com/e/
Project-URL: Repository, https://github.com/kor0p/BeePy
Project-URL: Docs, https://bee-py.readthedocs.io/en/latest/
Project-URL: Community, https://t.me/bee_py/
Project-URL: Sandbox, https://kor0p.github.io/BeePy-examples/sandbox
Project-URL: NPM, https://www.npmjs.com/package/@kor0p/beepy
Author-email: kor0p <3.kor0p@gmail.com>
License-File: LICENSE
Classifier: Operating System :: OS Independent
Classifier: Programming Language :: Python :: 3
Requires-Python: >=3.10.10
Requires-Dist: boltons==23.1.1
Requires-Dist: python-dotenv==1.0.0
Provides-Extra: contributing
Requires-Dist: pre-commit; extra == 'contributing'
Provides-Extra: dev
Requires-Dist: click==8.1.3; extra == 'dev'
Requires-Dist: micropip==0.3.0; extra == 'dev'
Requires-Dist: pyodide-py==0.25.1; extra == 'dev'
Requires-Dist: requests==2.31.0; extra == 'dev'
Requires-Dist: watchdog==3.0.0; extra == 'dev'
Requires-Dist: websockets==11.0.3; extra == 'dev'
Provides-Extra: docs
Requires-Dist: mkdocs-material==9.5.17; extra == 'docs'
Provides-Extra: ssr
Requires-Dist: selenium==4.19.0; extra == 'ssr'
